{
  "target_win": {
    "logreg": {
      "logloss_mean": 0.3468647589295519,
      "logloss_std": 0.003518064504649399,
      "brier_mean": 0.10626350423536524,
      "auc_mean": 0.8265647667891963,
      "auc_std": 0.004008454304827919,
      "fold_scores": [
        {
          "fold": 1,
          "n_train": 25181,
          "n_val": 25177,
          "pos_rate": 0.16928148707153354,
          "logloss": 0.35104466568923465,
          "brier": 0.10768335625678134,
          "auc": 0.821569854429669
        },
        {
          "fold": 2,
          "n_train": 50358,
          "n_val": 25177,
          "pos_rate": 0.16892401795289352,
          "logloss": 0.3498620081551463,
          "brier": 0.10731150195803645,
          "auc": 0.8231241563356292
        },
        {
          "fold": 3,
          "n_train": 75535,
          "n_val": 25177,
          "pos_rate": 0.1689637367438535,
          "logloss": 0.3453006308298604,
          "brier": 0.10564423116111679,
          "auc": 0.8286740975445351
        },
        {
          "fold": 4,
          "n_train": 100712,
          "n_val": 25177,
          "pos_rate": 0.1688445803709735,
          "logloss": 0.3411231787081227,
          "brier": 0.1045397134749471,
          "auc": 0.8328175189951988
        },
        {
          "fold": 5,
          "n_train": 125889,
          "n_val": 25177,
          "pos_rate": 0.16900345553481352,
          "logloss": 0.3469933112653957,
          "brier": 0.10613871832594454,
          "auc": 0.8266382066409498
        }
      ],
      "feature_importance": {},
      "calibration_curve": {
        "mean_pred": [
          0.0394537795076582,
          0.1449444727142923,
          0.24659721318769337,
          0.34645017022832786,
          0.4473050435212293,
          0.5474733403682726,
          0.6455676366780532,
          0.7353692774998305,
          0.8183268463544672
        ],
        "frac_pos": [
          0.04665681217763241,
          0.12466040172805416,
          0.20443751855149897,
          0.3146487294469357,
          0.4425758229121748,
          0.6058890147225368,
          0.7182001730602827,
          0.8089700996677741,
          0.75
        ]
      }
    },
    "randomforest": {
      "logloss_mean": 0.4927436523531038,
      "logloss_std": 0.009103572387967917,
      "brier_mean": 0.15904054045783628,
      "auc_mean": 0.8344358206706529,
      "auc_std": 0.003603874028383902,
      "fold_scores": [
        {
          "fold": 1,
          "n_train": 25181,
          "n_val": 25177,
          "pos_rate": 0.16928148707153354,
          "logloss": 0.4757975996885277,
          "brier": 0.15208249777028235,
          "auc": 0.8299599292032855
        },
        {
          "fold": 2,
          "n_train": 50358,
          "n_val": 25177,
          "pos_rate": 0.16892401795289352,
          "logloss": 0.4936961328237613,
          "brier": 0.15940243371800808,
          "auc": 0.8320305057080042
        },
        {
          "fold": 3,
          "n_train": 75535,
          "n_val": 25177,
          "pos_rate": 0.1689637367438535,
          "logloss": 0.4963270200415004,
          "brier": 0.16016662224864264,
          "auc": 0.8347406134940211
        },
        {
          "fold": 4,
          "n_train": 100712,
          "n_val": 25177,
          "pos_rate": 0.1688445803709735,
          "logloss": 0.4946795556627022,
          "brier": 0.15995592270336959,
          "auc": 0.8406738485649142
        },
        {
          "fold": 5,
          "n_train": 125889,
          "n_val": 25177,
          "pos_rate": 0.16900345553481352,
          "logloss": 0.5032179535490275,
          "brier": 0.16359522584887876,
          "auc": 0.8347742063830392
        }
      ],
      "feature_importance": {
        "boat_no": 0.5349409708410998,
        "nat_win_z": 0.12486216799467423,
        "national_win_rate": 0.05310770659559348,
        "national_top2_rate": 0.04485558173931146,
        "local_win_z": 0.04343752538228242,
        "national_top3_rate": 0.03754187091100269,
        "racer_class_num": 0.02421721035513992,
        "local_win_rate": 0.017291372464953925,
        "local_top2_rate": 0.013519119316705162,
        "race_no": 0.01145312369731114,
        "motor_top2_z": 0.010944213196065176,
        "local_top3_rate": 0.009885263166772374,
        "entry_course": 0.009646205593585455,
        "avg_st": 0.008130067496271352,
        "motor_top2_rate": 0.008041847029946859,
        "motor_top3_rate": 0.008002555247887197,
        "age": 0.007481079970793536,
        "boat_top2_z": 0.005663906061153372,
        "racer_weight": 0.005507971218018191,
        "stadium_code_num": 0.005048466130982169,
        "boat_top3_rate": 0.005036099277013294,
        "boat_top2_rate": 0.005010331881700218,
        "grade_num": 0.004344673708116963,
        "month": 0.000609288218583719,
        "f_count": 0.0006017998006381659,
        "penalty_total": 0.0005379893891538922,
        "distance": 0.00027699425047674256,
        "l_count": 4.599064767049857e-06,
        "is_night": 0.0,
        "is_saltwater": 0.0
      }
    },
    "lightgbm": {
      "logloss_mean": 0.4510134214148227,
      "logloss_std": 0.015432071505181503,
      "brier_mean": 0.1440550013731961,
      "auc_mean": 0.8384397820423679,
      "auc_std": 0.005652672397030599,
      "fold_scores": [
        {
          "fold": 1,
          "n_train": 25181,
          "n_val": 25177,
          "pos_rate": 0.16928148707153354,
          "logloss": 0.42195865390354337,
          "brier": 0.13325959431658302,
          "auc": 0.8307615021943638
        },
        {
          "fold": 2,
          "n_train": 50358,
          "n_val": 25177,
          "pos_rate": 0.16892401795289352,
          "logloss": 0.4525153225960958,
          "brier": 0.1445283389774404,
          "auc": 0.8326537177778138
        },
        {
          "fold": 3,
          "n_train": 75535,
          "n_val": 25177,
          "pos_rate": 0.1689637367438535,
          "logloss": 0.45266341338592203,
          "brier": 0.1442584986791298,
          "auc": 0.8423676906442346
        },
        {
          "fold": 4,
          "n_train": 100712,
          "n_val": 25177,
          "pos_rate": 0.1688445803709735,
          "logloss": 0.4657122865442954,
          "brier": 0.15008813313100522,
          "auc": 0.8450008659295732
        },
        {
          "fold": 5,
          "n_train": 125889,
          "n_val": 25177,
          "pos_rate": 0.16900345553481352,
          "logloss": 0.4622174306442571,
          "brier": 0.14814044176182212,
          "auc": 0.8414151336658537
        }
      ],
      "feature_importance": {
        "nat_win_z": 1131.6,
        "motor_top2_z": 1104.2,
        "local_win_z": 1019.2,
        "boat_top2_z": 984.2,
        "racer_weight": 811.0,
        "motor_top2_rate": 735.6,
        "boat_top2_rate": 716.2,
        "motor_top3_rate": 685.2,
        "boat_top3_rate": 684.2,
        "national_top2_rate": 678.8,
        "national_win_rate": 666.4,
        "age": 645.2,
        "boat_no": 632.6,
        "national_top3_rate": 591.8,
        "race_no": 568.4,
        "stadium_code_num": 559.8,
        "local_top2_rate": 502.8,
        "local_win_rate": 493.0,
        "local_top3_rate": 459.2,
        "avg_st": 392.6,
        "entry_course": 296.8,
        "grade_num": 123.0,
        "racer_class_num": 96.4,
        "month": 90.6,
        "f_count": 70.0,
        "distance": 57.6,
        "penalty_total": 24.6,
        "l_count": 12.8,
        "is_night": 0.0,
        "is_saltwater": 0.0
      }
    },
    "catboost": {
      "logloss_mean": 0.4686121043880049,
      "logloss_std": 0.012796280548976314,
      "brier_mean": 0.15038351565088423,
      "auc_mean": 0.8420451707825816,
      "auc_std": 0.003667110725048878,
      "fold_scores": [
        {
          "fold": 1,
          "n_train": 25181,
          "n_val": 25177,
          "pos_rate": 0.16928148707153354,
          "logloss": 0.4440385233475626,
          "brier": 0.14101047501766598,
          "auc": 0.8391258196541542
        },
        {
          "fold": 2,
          "n_train": 50358,
          "n_val": 25177,
          "pos_rate": 0.16892401795289352,
          "logloss": 0.4714388006511143,
          "brier": 0.1513967637402636,
          "auc": 0.8373771650971304
        },
        {
          "fold": 3,
          "n_train": 75535,
          "n_val": 25177,
          "pos_rate": 0.1689637367438535,
          "logloss": 0.4702749495873116,
          "brier": 0.15082553598995516,
          "auc": 0.8439425541805164
        },
        {
          "fold": 4,
          "n_train": 100712,
          "n_val": 25177,
          "pos_rate": 0.1688445803709735,
          "logloss": 0.47975492058934127,
          "brier": 0.15495588122935522,
          "auc": 0.8478174134379004
        },
        {
          "fold": 5,
          "n_train": 125889,
          "n_val": 25177,
          "pos_rate": 0.16900345553481352,
          "logloss": 0.4775533277646947,
          "brier": 0.15372892227718127,
          "auc": 0.841962901543206
        }
      ],
      "feature_importance": {
        "boat_no": 36.62709707477353,
        "nat_win_z": 9.049082246086488,
        "motor_top2_z": 3.8805415203528284,
        "local_win_z": 3.5979438001747623,
        "racer_weight": 3.5937056461214736,
        "age": 3.293535362054125,
        "national_top2_rate": 3.1749090353687044,
        "race_no": 3.006327729443407,
        "motor_top2_rate": 2.9261240530084405,
        "national_win_rate": 2.9161847117968334,
        "boat_top2_z": 2.7574464687352442,
        "stadium_code_num": 2.6998719098970754,
        "national_top3_rate": 2.5458277086932615,
        "boat_top2_rate": 2.5140816206264915,
        "motor_top3_rate": 2.454925826948725,
        "boat_top3_rate": 2.3729269423232062,
        "avg_st": 2.0914038262713093,
        "local_top2_rate": 1.8675828415679139,
        "local_top3_rate": 1.8058149070399054,
        "local_win_rate": 1.6735502528546842,
        "entry_course": 1.4207800913208557,
        "grade_num": 1.0348919849272245,
        "racer_class_num": 0.9488495412378155,
        "f_count": 0.5256819916816998,
        "penalty_total": 0.4301935334702396,
        "month": 0.4005784492863073,
        "distance": 0.3247872767298608,
        "l_count": 0.06535364720759344,
        "is_night": 0.0,
        "is_saltwater": 0.0
      }
    }
  },
  "target_top2": {
    "logreg": {
      "logloss_mean": 0.5127287553887125,
      "logloss_std": 0.004505565762510291,
      "brier_mean": 0.17054658066461528,
      "auc_mean": 0.7898778004858837,
      "auc_std": 0.004130956182674436,
      "fold_scores": [
        {
          "fold": 1,
          "n_train": 25181,
          "n_val": 25177,
          "pos_rate": 0.3386424117249871,
          "logloss": 0.5193784787751916,
          "brier": 0.1730582003251821,
          "auc": 0.7835353057348926
        },
        {
          "fold": 2,
          "n_train": 50358,
          "n_val": 25177,
          "pos_rate": 0.337768598323867,
          "logloss": 0.5137735354702638,
          "brier": 0.17093788324177547,
          "auc": 0.7891661892845724
        },
        {
          "fold": 3,
          "n_train": 75535,
          "n_val": 25177,
          "pos_rate": 0.33800691106962705,
          "logloss": 0.5122661564113871,
          "brier": 0.1703509137043205,
          "auc": 0.790534318573323
        },
        {
          "fold": 4,
          "n_train": 100712,
          "n_val": 25177,
          "pos_rate": 0.337649441950987,
          "logloss": 0.505251067227294,
          "brier": 0.1679147943150813,
          "auc": 0.7965185984497076
        },
        {
          "fold": 5,
          "n_train": 125889,
          "n_val": 25177,
          "pos_rate": 0.33800691106962705,
          "logloss": 0.5129745390594262,
          "brier": 0.17047111173671697,
          "auc": 0.7896345903869231
        }
      ],
      "feature_importance": {},
      "calibration_curve": {
        "mean_pred": [
          0.060888464270857964,
          0.14824854551732294,
          0.24816468268339972,
          0.34859205189246045,
          0.4488655720987219,
          0.5487469401123651,
          0.6481926351746505,
          0.7474497013327134,
          0.8343511542693763,
          0.9089097456417247
        ],
        "frac_pos": [
          0.05964253974523551,
          0.15169243627246135,
          0.2476464838726272,
          0.34344827586206894,
          0.4198612632347572,
          0.5299799843355669,
          0.6441027757713342,
          0.7853071564281191,
          0.8866896156052783,
          0.8888888888888888
        ]
      }
    },
    "randomforest": {
      "logloss_mean": 0.5598188052663228,
      "logloss_std": 0.0028960869130840216,
      "brier_mean": 0.1893491320486732,
      "auc_mean": 0.7869715945618634,
      "auc_std": 0.005986793295915516,
      "fold_scores": [
        {
          "fold": 1,
          "n_train": 25181,
          "n_val": 25177,
          "pos_rate": 0.3386424117249871,
          "logloss": 0.5618857767646278,
          "brier": 0.19035649973581992,
          "auc": 0.7777018490273186
        },
        {
          "fold": 2,
          "n_train": 50358,
          "n_val": 25177,
          "pos_rate": 0.337768598323867,
          "logloss": 0.5615543103774034,
          "brier": 0.18988829760321357,
          "auc": 0.7866645810998218
        },
        {
          "fold": 3,
          "n_train": 75535,
          "n_val": 25177,
          "pos_rate": 0.33800691106962705,
          "logloss": 0.5616387633663045,
          "brier": 0.19007313229267547,
          "auc": 0.7847139132422992
        },
        {
          "fold": 4,
          "n_train": 100712,
          "n_val": 25177,
          "pos_rate": 0.337649441950987,
          "logloss": 0.5542206438541586,
          "brier": 0.18696106247553387,
          "auc": 0.7958939700037829
        },
        {
          "fold": 5,
          "n_train": 125889,
          "n_val": 25177,
          "pos_rate": 0.33800691106962705,
          "logloss": 0.5597945319691197,
          "brier": 0.18946666813612326,
          "auc": 0.7898836594360944
        }
      ],
      "feature_importance": {
        "boat_no": 0.4336833484925945,
        "nat_win_z": 0.1565913564963786,
        "national_win_rate": 0.06962201085573909,
        "national_top2_rate": 0.05712222218107952,
        "national_top3_rate": 0.05525590696824961,
        "local_win_z": 0.05177047766614782,
        "racer_class_num": 0.03079835309654616,
        "local_win_rate": 0.02051517417588843,
        "local_top2_rate": 0.013736361262811006,
        "local_top3_rate": 0.013615110386112631,
        "motor_top2_z": 0.012818977233598147,
        "race_no": 0.009222645117509004,
        "motor_top2_rate": 0.008762548611741966,
        "avg_st": 0.008556077799791992,
        "motor_top3_rate": 0.008399520512270288,
        "entry_course": 0.008160396670066726,
        "age": 0.0076736122785971235,
        "grade_num": 0.006077498195078115,
        "boat_top2_z": 0.005696946600677429,
        "racer_weight": 0.00554938819050327,
        "boat_top3_rate": 0.005048847258228179,
        "boat_top2_rate": 0.004987062621909776,
        "stadium_code_num": 0.004164639719759988,
        "f_count": 0.0007252674918578932,
        "penalty_total": 0.0006789953424428029,
        "month": 0.0005650645811430113,
        "distance": 0.0001999114176418123,
        "l_count": 2.278775635116883e-06,
        "is_night": 0.0,
        "is_saltwater": 0.0
      }
    },
    "lightgbm": {
      "logloss_mean": 0.5398926554838624,
      "logloss_std": 0.003517027335962248,
      "brier_mean": 0.18168782495504726,
      "auc_mean": 0.7930811914329978,
      "auc_std": 0.0064205515820480305,
      "fold_scores": [
        {
          "fold": 1,
          "n_train": 25181,
          "n_val": 25177,
          "pos_rate": 0.3386424117249871,
          "logloss": 0.5437884323391542,
          "brier": 0.1831326120231289,
          "auc": 0.7820231806075051
        },
        {
          "fold": 2,
          "n_train": 50358,
          "n_val": 25177,
          "pos_rate": 0.337768598323867,
          "logloss": 0.5442242023864118,
          "brier": 0.18318351678360378,
          "auc": 0.7914186353306157
        },
        {
          "fold": 3,
          "n_train": 75535,
          "n_val": 25177,
          "pos_rate": 0.33800691106962705,
          "logloss": 0.5383390404433958,
          "brier": 0.18121239610770173,
          "auc": 0.7938358882646084
        },
        {
          "fold": 4,
          "n_train": 100712,
          "n_val": 25177,
          "pos_rate": 0.337649441950987,
          "logloss": 0.5352859356169082,
          "brier": 0.18006473790522143,
          "auc": 0.8011751837980259
        },
        {
          "fold": 5,
          "n_train": 125889,
          "n_val": 25177,
          "pos_rate": 0.33800691106962705,
          "logloss": 0.5378256666334422,
          "brier": 0.18084586195558058,
          "auc": 0.7969530691642336
        }
      ],
      "feature_importance": {
        "nat_win_z": 1164.4,
        "motor_top2_z": 1104.8,
        "local_win_z": 1019.8,
        "boat_top2_z": 978.0,
        "racer_weight": 832.2,
        "national_win_rate": 745.2,
        "national_top2_rate": 704.6,
        "motor_top2_rate": 679.2,
        "motor_top3_rate": 675.6,
        "national_top3_rate": 663.0,
        "boat_top3_rate": 651.6,
        "boat_top2_rate": 605.6,
        "boat_no": 605.4,
        "age": 592.6,
        "local_win_rate": 532.0,
        "race_no": 528.4,
        "stadium_code_num": 517.8,
        "local_top2_rate": 488.2,
        "local_top3_rate": 458.8,
        "avg_st": 372.2,
        "entry_course": 240.6,
        "racer_class_num": 134.8,
        "grade_num": 119.6,
        "month": 102.4,
        "f_count": 68.4,
        "penalty_total": 36.8,
        "distance": 34.2,
        "l_count": 4.2,
        "is_night": 0.0,
        "is_saltwater": 0.0
      }
    },
    "catboost": {
      "logloss_mean": 0.7158561549898665,
      "logloss_std": 0.008150106280997901,
      "brier_mean": 0.2530161275027559,
      "auc_mean": 0.7957576538416916,
      "auc_std": 0.005199869540660352,
      "fold_scores": [
        {
          "fold": 1,
          "n_train": 25181,
          "n_val": 25177,
          "pos_rate": 0.3386424117249871,
          "logloss": 0.7000689896680874,
          "brier": 0.2468861039400155,
          "auc": 0.7866965531695501
        },
        {
          "fold": 2,
          "n_train": 50358,
          "n_val": 25177,
          "pos_rate": 0.337768598323867,
          "logloss": 0.7213823522892919,
          "brier": 0.255228442135874,
          "auc": 0.7945843726138536
        },
        {
          "fold": 3,
          "n_train": 75535,
          "n_val": 25177,
          "pos_rate": 0.33800691106962705,
          "logloss": 0.7158851800967636,
          "brier": 0.25316969862814176,
          "auc": 0.7969511796603082
        },
        {
          "fold": 4,
          "n_train": 100712,
          "n_val": 25177,
          "pos_rate": 0.337649441950987,
          "logloss": 0.7209886506576757,
          "brier": 0.2548640677497196,
          "auc": 0.8024483397872654
        },
        {
          "fold": 5,
          "n_train": 125889,
          "n_val": 25177,
          "pos_rate": 0.33800691106962705,
          "logloss": 0.7209556022375135,
          "brier": 0.2549323250600288,
          "auc": 0.7981078239774805
        }
      ],
      "feature_importance": {
        "boat_no": 36.23741085106291,
        "nat_win_z": 12.449153188998851,
        "local_win_z": 3.851671342601714,
        "racer_weight": 3.7890706682858037,
        "national_top3_rate": 3.6462028758504674,
        "motor_top2_z": 3.329216073532353,
        "national_top2_rate": 3.267729794065344,
        "national_win_rate": 3.1135756589723433,
        "age": 2.8060860961682885,
        "race_no": 2.5701182381945253,
        "boat_top2_z": 2.425723569522307,
        "stadium_code_num": 2.418280196254552,
        "motor_top3_rate": 2.2342194165303333,
        "avg_st": 2.0984862841611682,
        "motor_top2_rate": 2.049831172838881,
        "boat_top3_rate": 1.8931410890482212,
        "local_top3_rate": 1.7390312891532638,
        "racer_class_num": 1.6949247993587935,
        "local_win_rate": 1.6799862686394267,
        "boat_top2_rate": 1.5764467496876189,
        "local_top2_rate": 1.2827520878424177,
        "grade_num": 1.2058600873300125,
        "entry_course": 1.0177227925775245,
        "f_count": 0.5318551684129957,
        "month": 0.406780528601873,
        "penalty_total": 0.40411903393644943,
        "distance": 0.22690489884887724,
        "l_count": 0.05369977952267853,
        "is_night": 0.0,
        "is_saltwater": 0.0
      }
    }
  },
  "target_top3": {
    "logreg": {
      "logloss_mean": 0.5743196730904088,
      "logloss_std": 0.005912498936424416,
      "brier_mean": 0.19619257511459537,
      "auc_mean": 0.7671132475686784,
      "auc_std": 0.005799691938492942,
      "fold_scores": [
        {
          "fold": 1,
          "n_train": 25181,
          "n_val": 25177,
          "pos_rate": 0.5078841800055607,
          "logloss": 0.5827743442526648,
          "brier": 0.19958733143185026,
          "auc": 0.7585993719786912
        },
        {
          "fold": 2,
          "n_train": 50358,
          "n_val": 25177,
          "pos_rate": 0.5065734599038805,
          "logloss": 0.5763588219358288,
          "brier": 0.19701165283372243,
          "auc": 0.7653723193299453
        },
        {
          "fold": 3,
          "n_train": 75535,
          "n_val": 25177,
          "pos_rate": 0.5070103666044405,
          "logloss": 0.5742262424323129,
          "brier": 0.1961312413180537,
          "auc": 0.7670986494628412
        },
        {
          "fold": 4,
          "n_train": 100712,
          "n_val": 25177,
          "pos_rate": 0.5064543035310005,
          "logloss": 0.5643731194273449,
          "brier": 0.19229296554493308,
          "auc": 0.7767164327902352
        },
        {
          "fold": 5,
          "n_train": 125889,
          "n_val": 25177,
          "pos_rate": 0.5069706478134806,
          "logloss": 0.5738658374038921,
          "brier": 0.1959396844444173,
          "auc": 0.7677794642816793
        }
      ],
      "feature_importance": {}
    },
    "randomforest": {
      "logloss_mean": 0.5813692056172177,
      "logloss_std": 0.005672442951658384,
      "brier_mean": 0.19895894733135386,
      "auc_mean": 0.7647472562650265,
      "auc_std": 0.007420762056851566,
      "fold_scores": [
        {
          "fold": 1,
          "n_train": 25181,
          "n_val": 25177,
          "pos_rate": 0.5078841800055607,
          "logloss": 0.5896013768177492,
          "brier": 0.20263384899536305,
          "auc": 0.7528881639462699
        },
        {
          "fold": 2,
          "n_train": 50358,
          "n_val": 25177,
          "pos_rate": 0.5065734599038805,
          "logloss": 0.5832535422282961,
          "brier": 0.19964060239663403,
          "auc": 0.7636604033772612
        },
        {
          "fold": 3,
          "n_train": 75535,
          "n_val": 25177,
          "pos_rate": 0.5070103666044405,
          "logloss": 0.582559675212529,
          "brier": 0.1995038374095047,
          "auc": 0.763633717367131
        },
        {
          "fold": 4,
          "n_train": 100712,
          "n_val": 25177,
          "pos_rate": 0.5064543035310005,
          "logloss": 0.5722355882406537,
          "brier": 0.19509839835954876,
          "auc": 0.7758662960674176
        },
        {
          "fold": 5,
          "n_train": 125889,
          "n_val": 25177,
          "pos_rate": 0.5069706478134806,
          "logloss": 0.5791958455868611,
          "brier": 0.19791804949571873,
          "auc": 0.7676877005670528
        }
      ],
      "feature_importance": {
        "boat_no": 0.3128773668036918,
        "nat_win_z": 0.2086523566201584,
        "national_win_rate": 0.08567391246517461,
        "national_top3_rate": 0.0740903933925552,
        "local_win_z": 0.06266462595616847,
        "national_top2_rate": 0.05927580849456775,
        "racer_class_num": 0.03572291227644202,
        "local_win_rate": 0.023863011129468165,
        "local_top3_rate": 0.017119207711748515,
        "motor_top2_z": 0.014539590087117363,
        "local_top2_rate": 0.014470619310857141,
        "age": 0.010033576839297039,
        "motor_top2_rate": 0.0099242991395752,
        "motor_top3_rate": 0.009294635695666669,
        "race_no": 0.009214673687719086,
        "grade_num": 0.008141690082383534,
        "avg_st": 0.008098249190197969,
        "boat_top2_z": 0.006262206700531822,
        "racer_weight": 0.006231204409758701,
        "entry_course": 0.006028831209663882,
        "boat_top3_rate": 0.005635381616984446,
        "boat_top2_rate": 0.0054860591171586905,
        "stadium_code_num": 0.003990540553724129,
        "penalty_total": 0.0009644352021496546,
        "f_count": 0.000907571984032654,
        "month": 0.0006098445878460768,
        "distance": 0.00022683781834757698,
        "l_count": 1.5791701334404135e-07,
        "is_night": 0.0,
        "is_saltwater": 0.0
      }
    },
    "lightgbm": {
      "logloss_mean": 0.5726754417088922,
      "logloss_std": 0.009658873167028587,
      "brier_mean": 0.19574946932681359,
      "auc_mean": 0.7680980747985753,
      "auc_std": 0.008515283850333765,
      "fold_scores": [
        {
          "fold": 1,
          "n_train": 25181,
          "n_val": 25177,
          "pos_rate": 0.5078841800055607,
          "logloss": 0.5898778299530391,
          "brier": 0.20232351480191013,
          "auc": 0.7531999338765479
        },
        {
          "fold": 2,
          "n_train": 50358,
          "n_val": 25177,
          "pos_rate": 0.5065734599038805,
          "logloss": 0.5745689432761935,
          "brier": 0.1964938469191712,
          "auc": 0.7660761373643263
        },
        {
          "fold": 3,
          "n_train": 75535,
          "n_val": 25177,
          "pos_rate": 0.5070103666044405,
          "logloss": 0.570399450939781,
          "brier": 0.1949718299927313,
          "auc": 0.769605586194021
        },
        {
          "fold": 4,
          "n_train": 100712,
          "n_val": 25177,
          "pos_rate": 0.5064543035310005,
          "logloss": 0.5610774670217543,
          "brier": 0.19130228969294436,
          "auc": 0.7785847593804258
        },
        {
          "fold": 5,
          "n_train": 125889,
          "n_val": 25177,
          "pos_rate": 0.5069706478134806,
          "logloss": 0.5674535173536933,
          "brier": 0.19365586522731087,
          "auc": 0.7730239571775559
        }
      ],
      "feature_importance": {
        "nat_win_z": 1205.4,
        "motor_top2_z": 1053.0,
        "local_win_z": 1000.0,
        "boat_top2_z": 961.0,
        "racer_weight": 845.4,
        "national_win_rate": 780.6,
        "national_top2_rate": 702.0,
        "motor_top2_rate": 697.0,
        "boat_top3_rate": 690.4,
        "national_top3_rate": 690.2,
        "motor_top3_rate": 663.6,
        "boat_top2_rate": 631.6,
        "age": 614.2,
        "local_win_rate": 555.4,
        "local_top3_rate": 530.2,
        "boat_no": 528.6,
        "stadium_code_num": 519.8,
        "local_top2_rate": 519.2,
        "race_no": 479.6,
        "avg_st": 329.0,
        "entry_course": 217.0,
        "grade_num": 129.2,
        "racer_class_num": 124.8,
        "month": 94.4,
        "f_count": 73.8,
        "penalty_total": 45.4,
        "distance": 32.2,
        "l_count": 6.8,
        "is_night": 0.0,
        "is_saltwater": 0.0
      },
      "calibration_curve": {
        "mean_pred": [
          0.049399335383262646,
          0.1551797926854379,
          0.2511873309911386,
          0.3506631123345248,
          0.4500304488277218,
          0.5502886903817552,
          0.64879319949443,
          0.7481214182244011,
          0.8508572131823294,
          0.9292857889995101
        ],
        "frac_pos": [
          0.06464427591188154,
          0.17808483911489031,
          0.2719124911785462,
          0.3663822631873949,
          0.46040917398738285,
          0.5496716417910448,
          0.6412969070881822,
          0.7369935267321985,
          0.8426597081279598,
          0.9286215117094376
        ]
      }
    },
    "catboost": {
      "logloss_mean": 0.7895843665695859,
      "logloss_std": 0.005143883348810016,
      "brier_mean": 0.2756496522048907,
      "auc_mean": 0.7711284711232953,
      "auc_std": 0.006823341246923986,
      "fold_scores": [
        {
          "fold": 1,
          "n_train": 25181,
          "n_val": 25177,
          "pos_rate": 0.5078841800055607,
          "logloss": 0.7802316673049303,
          "brier": 0.27184576829374185,
          "auc": 0.7600939601882031
        },
        {
          "fold": 2,
          "n_train": 50358,
          "n_val": 25177,
          "pos_rate": 0.5065734599038805,
          "logloss": 0.7952171423862828,
          "brier": 0.27796926008176354,
          "auc": 0.7688777957682709
        },
        {
          "fold": 3,
          "n_train": 75535,
          "n_val": 25177,
          "pos_rate": 0.5070103666044405,
          "logloss": 0.7922939103995351,
          "brier": 0.2768026453453371,
          "auc": 0.7716642373433137
        },
        {
          "fold": 4,
          "n_train": 100712,
          "n_val": 25177,
          "pos_rate": 0.5064543035310005,
          "logloss": 0.7884702245191637,
          "brier": 0.2753448746550961,
          "auc": 0.780996249739482
        },
        {
          "fold": 5,
          "n_train": 125889,
          "n_val": 25177,
          "pos_rate": 0.5069706478134806,
          "logloss": 0.7917088882380174,
          "brier": 0.27628571264851476,
          "auc": 0.774010112577207
        }
      ],
      "feature_importance": {
        "boat_no": 34.829208901904266,
        "nat_win_z": 15.783431916375335,
        "local_win_z": 4.2389407307611275,
        "national_top3_rate": 4.113053290315934,
        "national_top2_rate": 3.960377539852609,
        "racer_weight": 3.5169081644402085,
        "national_win_rate": 3.3652395915028697,
        "motor_top2_z": 3.1412997464999184,
        "age": 2.551763657827578,
        "boat_top2_z": 2.2063844714665644,
        "stadium_code_num": 2.016760494289424,
        "racer_class_num": 1.8543564712870981,
        "avg_st": 1.8377844581371867,
        "race_no": 1.8369526687117044,
        "boat_top3_rate": 1.8271963875366197,
        "motor_top3_rate": 1.7660342843881573,
        "local_top3_rate": 1.649491598809113,
        "motor_top2_rate": 1.5602020692829213,
        "local_win_rate": 1.5178678491784403,
        "boat_top2_rate": 1.410293671518692,
        "local_top2_rate": 1.386556129690624,
        "grade_num": 1.2484195886737477,
        "entry_course": 0.8567642754401963,
        "f_count": 0.5232558415771271,
        "penalty_total": 0.48703351520281474,
        "month": 0.31816665569275654,
        "distance": 0.14802278676007827,
        "l_count": 0.048233242876896995,
        "is_night": 0.0,
        "is_saltwater": 0.0
      }
    }
  }
}